mensajes/__init__.py
mensajes/Hola/__init__.py
mensajes/Hola/saludo.py
mensajes/adios/__init__.py
mensajes/adios/despedidas.py
tests/__init__.py
tests/test_hola.py
mensajes_caraldana2024-6.0.dist-info/LICENSE
mensajes_caraldana2024-6.0.dist-info/METADATA
mensajes_caraldana2024-6.0.dist-info/WHEEL
mensajes_caraldana2024-6.0.dist-info/top_level.txt
mensajes_caraldana2024-6.0.dist-info/RECORD
