Metadata-Version: 2.1
Name: mensajes-caraldana2024
Version: 6.0
Summary: un paquete para saludar y despedir
Home-page: https://www.hektor.dev
Author: Héctor Costa Guzmán
Author-email: hola@hektor.dev
Classifier: Environment :: Console
Classifier: Intended Audience :: Developers
Classifier: License :: OSI Approved :: MIT License
Classifier: Operating System :: OS Independent
Classifier: Programming Language :: Python
Classifier: Programming Language :: Python :: 3.12
Classifier: Topic :: Utilities
License-File: LICENSE
Requires-Dist: numpy >=1.25.2
